[
  {
    "issue": 0,
    "count": 141580
  },
  {
    "issue": 1,
    "count": 182994
  },
  {
    "issue": 2,
    "count": 82031
  },
  {
    "issue": 3,
    "count": 72820
  },
  {
    "issue": 4,
    "count": 63120
  },
  {
    "issue": 5,
    "count": 98656
  },
  {
    "issue": 6,
    "count": 96083
  },
  {
    "issue": 7,
    "count": 125522
  },
  {
    "issue": 8,
    "count": 107550
  },
  {
    "issue": 9,
    "count": 101790
  },
  {
    "issue": 10,
    "count": 92032
  },
  {
    "issue": 11,
    "count": 99231
  },
  {
    "issue": 12,
    "count": 99528
  },
  {
    "issue": 13,
    "count": 98692
  },
  {
    "issue": 14,
    "count": 92522
  },
  {
    "issue": 15,
    "count": 94076
  },
  {
    "issue": 16,
    "count": 97498
  },
  {
    "issue": 17,
    "count": 93544
  },
  {
    "issue": 18,
    "count": 84217
  },
  {
    "issue": 19,
    "count": 88507
  },
  {
    "issue": 20,
    "count": 80307
  },
  {
    "issue": 21,
    "count": 78416
  },
  {
    "issue": 22,
    "count": 80891
  },
  {
    "issue": 23,
    "count": 90725
  },
  {
    "issue": 24,
    "count": 65946
  },
  {
    "issue": 25,
    "count": 72902
  },
  {
    "issue": 26,
    "count": 71390
  },
  {
    "issue": 27,
    "count": 74020
  },
  {
    "issue": 28,
    "count": 62449
  },
  {
    "issue": 29,
    "count": 74240
  },
  {
    "issue": 30,
    "count": 62187
  },
  {
    "issue": 31,
    "count": 16538
  },
  {
    "issue": 32,
    "count": 16475
  },
  {
    "issue": 33,
    "count": 16059
  },
  {
    "issue": 34,
    "count": 15651
  },
  {
    "issue": 35,
    "count": 15336
  },
  {
    "issue": 36,
    "count": 14860
  },
  {
    "issue": 37,
    "count": 14586
  },
  {
    "issue": 38,
    "count": 14280
  }
]