[
  {
    "issue": 7,
    "count": 4980
  },
  {
    "issue": 8,
    "count": 5191
  },
  {
    "issue": 9,
    "count": 5195
  },
  {
    "issue": 10,
    "count": 5347
  },
  {
    "issue": 13,
    "count": 5049
  },
  {
    "issue": 14,
    "count": 4977
  },
  {
    "issue": 15,
    "count": 5221
  },
  {
    "issue": 16,
    "count": 5222
  },
  {
    "issue": 17,
    "count": 5203
  },
  {
    "issue": 18,
    "count": 5321
  },
  {
    "issue": 19,
    "count": 5421
  },
  {
    "issue": 20,
    "count": 5109
  },
  {
    "issue": 21,
    "count": 5194
  },
  {
    "issue": 22,
    "count": 5248
  },
  {
    "issue": 23,
    "count": 5123
  },
  {
    "issue": 24,
    "count": 4930
  },
  {
    "issue": 25,
    "count": 4832
  },
  {
    "issue": 26,
    "count": 4834
  },
  {
    "issue": 27,
    "count": 4836
  },
  {
    "issue": 28,
    "count": 4772
  },
  {
    "issue": 29,
    "count": 4566
  },
  {
    "issue": 30,
    "count": 4380
  },
  {
    "issue": 31,
    "count": 4371
  },
  {
    "issue": 32,
    "count": 4271
  },
  {
    "issue": 33,
    "count": 8302
  },
  {
    "issue": 34,
    "count": 7651
  }
]