{"records":[{"issue":1,"count":31504},{"issue":2,"count":22688},{"issue":3,"count":19190},{"issue":4,"count":17191},{"issue":5,"count":15877},{"issue":6,"count":14878},{"issue":7,"count":13648},{"issue":8,"count":12784},{"issue":9,"count":12072},{"issue":10,"count":11625},{"issue":11,"count":11125},{"issue":12,"count":10611},{"issue":13,"count":9976},{"issue":14,"count":9421},{"issue":15,"count":8929},{"issue":16,"count":8475},{"issue":17,"count":8180},{"issue":18,"count":7700},{"issue":19,"count":7543},{"issue":20,"count":7040}],"id":"plastic-man-dc","title":"Plastic Man","publisher":"DC"}