[
  {
    "year": 2006,
    "month": 10,
    "count": 23526
  },
  {
    "year": 2006,
    "month": 11,
    "count": 17378
  },
  {
    "year": 2006,
    "month": 12,
    "count": 14045
  },
  {
    "year": 2007,
    "month": 1,
    "count": 12143
  },
  {
    "year": 2007,
    "month": 2,
    "count": 10552
  },
  {
    "year": 2007,
    "month": 3,
    "count": 9740
  },
  {
    "year": 2015,
    "month": 6,
    "count": 30158
  },
  {
    "year": 2015,
    "month": 7,
    "count": 17093
  },
  {
    "year": 2015,
    "month": 8,
    "count": 13246
  },
  {
    "year": 2015,
    "month": 9,
    "count": 11302
  },
  {
    "year": 2015,
    "month": 10,
    "count": 10532
  },
  {
    "year": 2015,
    "month": 11,
    "count": 9709
  },
  {
    "year": 2015,
    "month": 12,
    "count": 9251
  },
  {
    "year": 2016,
    "month": 1,
    "count": 8864
  },
  {
    "year": 2016,
    "month": 3,
    "count": 17093
  },
  {
    "year": 2016,
    "month": 4,
    "count": 8281
  },
  {
    "year": 2016,
    "month": 5,
    "count": 8218
  }
]