[
  {
    "id": "amazing-spider-man-marvel",
    "rank": 1,
    "title": "Amazing Spider-Man",
    "issue": 700,
    "price": "$7.99",
    "publisher": "Marvel",
    "count": 200966
  },
  {
    "id": "avengers-marvel",
    "rank": 2,
    "title": "Avengers",
    "issue": 1,
    "price": "$3.99",
    "publisher": "Marvel",
    "count": 186989
  },
  {
    "id": "batman-dc",
    "rank": 3,
    "title": "Batman",
    "issue": 15,
    "price": "$3.99",
    "publisher": "DC",
    "count": 151568
  },
  {
    "id": "justice-league-dc",
    "rank": 4,
    "title": "Justice League",
    "issue": 15,
    "price": "$3.99",
    "publisher": "DC",
    "count": 115074
  },
  {
    "id": "detective-comics-dc",
    "rank": 5,
    "title": "Detective Comics",
    "issue": 15,
    "price": "$3.99",
    "publisher": "DC",
    "count": 106395
  },
  {
    "id": "avengers-marvel",
    "rank": 6,
    "title": "Avengers",
    "issue": 2,
    "price": "$3.99",
    "publisher": "Marvel",
    "count": 93894
  },
  {
    "id": "cable-and-x-force-marvel",
    "rank": 7,
    "title": "Cable And X-Force",
    "issue": 1,
    "price": "$3.99",
    "publisher": "Marvel",
    "count": 90334
  },
  {
    "id": "batman-and-robin-dc",
    "rank": 8,
    "title": "Batman And Robin",
    "issue": 15,
    "price": "$2.99",
    "publisher": "DC",
    "count": 89878
  },
  {
    "id": "all-new-x-men-marvel",
    "rank": 9,
    "title": "All New X-Men",
    "issue": 3,
    "price": "$3.99",
    "publisher": "Marvel",
    "count": 83798
  },
  {
    "id": "thunderbolts-marvel",
    "rank": 10,
    "title": "Thunderbolts",
    "issue": 1,
    "price": "$2.99",
    "publisher": "Marvel",
    "count": 83396
  },
  {
    "id": "all-new-x-men-marvel",
    "rank": 11,
    "title": "All New X-Men",
    "issue": 4,
    "price": "$3.99",
    "publisher": "Marvel",
    "count": 80665
  },
  {
    "id": "aquaman-dc",
    "rank": 12,
    "title": "Aquaman",
    "issue": 15,
    "price": "$2.99",
    "publisher": "DC",
    "count": 75947
  },
  {
    "id": "batgirl-dc",
    "rank": 13,
    "title": "Batgirl",
    "issue": 15,
    "price": "$2.99",
    "publisher": "DC",
    "count": 75341
  },
  {
    "id": "amazing-spider-man-marvel",
    "rank": 14,
    "title": "Amazing Spider-Man",
    "issue": 699,
    "price": "$3.99",
    "publisher": "Marvel",
    "count": 74904
  },
  {
    "id": "nightwing-dc",
    "rank": 15,
    "title": "Nightwing",
    "issue": 15,
    "price": "$2.99",
    "publisher": "DC",
    "count": 74407
  },
  {
    "id": "green-lantern-dc",
    "rank": 16,
    "title": "Green Lantern",
    "issue": 15,
    "price": "$2.99",
    "publisher": "DC",
    "count": 74363
  },
  {
    "id": "teen-titans-dc",
    "rank": 17,
    "title": "Teen Titans",
    "issue": 15,
    "price": "$2.99",
    "publisher": "DC",
    "count": 68707
  },
  {
    "id": "amazing-spider-man-marvel",
    "rank": 18,
    "title": "Amazing Spider-Man",
    "issue": 699,
    "price": "$2.99",
    "publisher": "Marvel",
    "count": 66245
  },
  {
    "id": "avengers-arena-marvel",
    "rank": 19,
    "title": "Avengers Arena",
    "issue": 1,
    "price": "$2.99",
    "publisher": "Marvel",
    "count": 64626
  },
  {
    "id": "captain-america-marvel",
    "rank": 20,
    "title": "Captain America",
    "issue": 2,
    "price": "$3.99",
    "publisher": "Marvel",
    "count": 64377
  },
  {
    "id": "red-hood-and-the-outlaws-dc",
    "rank": 21,
    "title": "Red Hood And The Outlaws",
    "issue": 15,
    "price": "$2.99",
    "publisher": "DC",
    "count": 64103
  },
  {
    "id": "indestructible-hulk-marvel",
    "rank": 22,
    "title": "Indestructible Hulk",
    "issue": 2,
    "price": "$3.99",
    "publisher": "Marvel",
    "count": 63653
  },
  {
    "id": "action-comics-dc",
    "rank": 23,
    "title": "Action Comics",
    "issue": 15,
    "price": "$3.99",
    "publisher": "DC",
    "count": 61298
  },
  {
    "id": "batman-the-dark-knight-dc",
    "rank": 24,
    "title": "Batman The Dark Knight",
    "issue": 15,
    "price": "$2.99",
    "publisher": "DC",
    "count": 60569
  },
  {
    "id": "deadpool-marvel",
    "rank": 25,
    "title": "Deadpool",
    "issue": 3,
    "price": "$2.99",
    "publisher": "Marvel",
    "count": 60215
  },
  {
    "id": "iron-man-marvel",
    "rank": 26,
    "title": "Iron Man",
    "issue": 3,
    "price": "$3.99",
    "publisher": "Marvel",
    "count": 59041
  },
  {
    "id": "fantastic-four-marvel",
    "rank": 27,
    "title": "Fantastic Four",
    "issue": 2,
    "price": "$2.99",
    "publisher": "Marvel",
    "count": 58421
  },
  {
    "id": "walking-dead-image",
    "rank": 28,
    "title": "Walking Dead",
    "issue": 105,
    "price": "$2.99",
    "publisher": "Image",
    "count": 57781
  },
  {
    "id": "cable-and-x-force-marvel",
    "rank": 29,
    "title": "Cable And X-Force",
    "issue": 2,
    "price": "$3.99",
    "publisher": "Marvel",
    "count": 57719
  },
  {
    "id": "suicide-squad-dc",
    "rank": 30,
    "title": "Suicide Squad",
    "issue": 15,
    "price": "$2.99",
    "publisher": "DC",
    "count": 57132
  },
  {
    "id": "iron-man-marvel",
    "rank": 31,
    "title": "Iron Man",
    "issue": 4,
    "price": "$3.99",
    "publisher": "Marvel",
    "count": 56708
  },
  {
    "id": "a-plus-x-marvel",
    "rank": 32,
    "title": "A Plus X",
    "issue": 3,
    "price": "$3.99",
    "publisher": "Marvel",
    "count": 56700
  },
  {
    "id": "thor-god-of-thunder-marvel",
    "rank": 33,
    "title": "Thor God of Thunder",
    "issue": 3,
    "price": "$3.99",
    "publisher": "Marvel",
    "count": 55547
  },
  {
    "id": "earth-2-dc",
    "rank": 34,
    "title": "Earth 2",
    "issue": 7,
    "price": "$2.99",
    "publisher": "DC",
    "count": 54409
  },
  {
    "id": "before-watchmen-rorschach-dc",
    "rank": 35,
    "title": "Before Watchmen Rorschach",
    "issue": 3,
    "price": "$3.99",
    "publisher": "DC",
    "count": 53396
  },
  {
    "id": "batman-incorporated-dc",
    "rank": 36,
    "title": "Batman Incorporated",
    "issue": 6,
    "price": "$2.99",
    "publisher": "DC",
    "count": 52636
  },
  {
    "id": "superman-dc",
    "rank": 37,
    "title": "Superman",
    "issue": 15,
    "price": "$2.99",
    "publisher": "DC",
    "count": 51225
  },
  {
    "id": "thunderbolts-marvel",
    "rank": 38,
    "title": "Thunderbolts",
    "issue": 2,
    "price": "$2.99",
    "publisher": "Marvel",
    "count": 50897
  },
  {
    "id": "before-watchmen-comedian-dc",
    "rank": 39,
    "title": "Before Watchmen Comedian",
    "issue": 4,
    "price": "$3.99",
    "publisher": "DC",
    "count": 50073
  },
  {
    "id": "before-watchmen-dr-manhattan-dc",
    "rank": 40,
    "title": "Before Watchmen Dr Manhattan",
    "issue": 3,
    "price": "$3.99",
    "publisher": "DC",
    "count": 48909
  },
  {
    "id": "green-lantern-corps-dc",
    "rank": 41,
    "title": "Green Lantern Corps",
    "issue": 15,
    "price": "$2.99",
    "publisher": "DC",
    "count": 47841
  },
  {
    "id": "uncanny-x-force-marvel",
    "rank": 42,
    "title": "Uncanny X-Force",
    "issue": 35,
    "price": "$3.99",
    "publisher": "Marvel",
    "count": 47736
  },
  {
    "id": "before-watchmen-minutemen-dc",
    "rank": 43,
    "title": "Before Watchmen Minutemen",
    "issue": 5,
    "price": "$3.99",
    "publisher": "DC",
    "count": 47627
  },
  {
    "id": "before-watchmen-nite-owl-dc",
    "rank": 44,
    "title": "Before Watchmen Nite Owl",
    "issue": 4,
    "price": "$3.99",
    "publisher": "DC",
    "count": 46928
  },
  {
    "id": "ff-marvel",
    "rank": 45,
    "title": "FF",
    "issue": 2,
    "price": "$2.99",
    "publisher": "Marvel",
    "count": 46096
  },
  {
    "id": "flash-dc",
    "rank": 46,
    "title": "Flash",
    "issue": 15,
    "price": "$2.99",
    "publisher": "DC",
    "count": 45925
  },
  {
    "id": "wolverine-and-x-men-marvel",
    "rank": 47,
    "title": "Wolverine And X-Men",
    "issue": 22,
    "price": "$3.99",
    "publisher": "Marvel",
    "count": 45658
  },
  {
    "id": "x-men-legacy-marvel",
    "rank": 48,
    "title": "X-Men Legacy",
    "issue": 3,
    "price": "$2.99",
    "publisher": "Marvel",
    "count": 45407
  },
  {
    "id": "green-lantern-new-guardians-dc",
    "rank": 49,
    "title": "Green Lantern New Guardians",
    "issue": 15,
    "price": "$2.99",
    "publisher": "DC",
    "count": 45136
  },
  {
    "id": "avengers-arena-marvel",
    "rank": 50,
    "title": "Avengers Arena",
    "issue": 2,
    "price": "$2.99",
    "publisher": "Marvel",
    "count": 43014
  },
  {
    "id": "saga-image",
    "rank": 51,
    "title": "Saga",
    "issue": 8,
    "price": "$2.99",
    "publisher": "Image",
    "count": 42324
  },
  {
    "id": "wonder-woman-dc",
    "rank": 52,
    "title": "Wonder Woman",
    "issue": 15,
    "price": "$2.99",
    "publisher": "DC",
    "count": 41641
  },
  {
    "id": "avenging-spider-man-marvel",
    "rank": 53,
    "title": "Avenging Spider-Man",
    "issue": 15,
    "price": "$2.99",
    "publisher": "Marvel",
    "count": 41504
  },
  {
    "id": "my-little-pony-friendship-is-magic-idw",
    "rank": 54,
    "title": "My Little Pony Friendship Is Magic",
    "issue": 2,
    "price": "$3.99",
    "publisher": "IDW",
    "count": 39841
  },
  {
    "id": "red-lanterns-dc",
    "rank": 55,
    "title": "Red Lanterns",
    "issue": 15,
    "price": "$2.99",
    "publisher": "DC",
    "count": 39071
  },
  {
    "id": "before-watchmen-moloch-dc",
    "rank": 56,
    "title": "Before Watchmen Moloch",
    "issue": 2,
    "price": "$3.99",
    "publisher": "DC",
    "count": 37371
  },
  {
    "id": "ultimate-comics-spider-man-marvel",
    "rank": 57,
    "title": "Ultimate Comics Spider-Man",
    "issue": 18,
    "price": "$3.99",
    "publisher": "Marvel",
    "count": 36944
  },
  {
    "id": "daredevil-marvel",
    "rank": 58,
    "title": "Daredevil",
    "issue": 21,
    "price": "$2.99",
    "publisher": "Marvel",
    "count": 35848
  },
  {
    "id": "catwoman-dc",
    "rank": 59,
    "title": "Catwoman",
    "issue": 15,
    "price": "$2.99",
    "publisher": "DC",
    "count": 35020
  },
  {
    "id": "batwoman-dc",
    "rank": 60,
    "title": "Batwoman",
    "issue": 15,
    "price": "$2.99",
    "publisher": "DC",
    "count": 34964
  },
  {
    "id": "hawkeye-marvel",
    "rank": 61,
    "title": "Hawkeye",
    "issue": 5,
    "price": "$2.99",
    "publisher": "Marvel",
    "count": 34385
  },
  {
    "id": "wolverine-marvel",
    "rank": 62,
    "title": "Wolverine",
    "issue": 317,
    "price": "$3.99",
    "publisher": "Marvel",
    "count": 34367
  },
  {
    "id": "avengers-assemble-marvel",
    "rank": 63,
    "title": "Avengers Assemble",
    "issue": 10,
    "price": "$3.99",
    "publisher": "Marvel",
    "count": 34035
  },
  {
    "id": "swamp-thing-dc",
    "rank": 64,
    "title": "Swamp Thing",
    "issue": 15,
    "price": "$2.99",
    "publisher": "DC",
    "count": 33916
  },
  {
    "id": "hawkeye-marvel",
    "rank": 65,
    "title": "Hawkeye",
    "issue": 6,
    "price": "$2.99",
    "publisher": "Marvel",
    "count": 33440
  },
  {
    "id": "animal-man-dc",
    "rank": 66,
    "title": "Animal Man",
    "issue": 15,
    "price": "$2.99",
    "publisher": "DC",
    "count": 32013
  },
  {
    "id": "worlds-finest-dc",
    "rank": 67,
    "title": "Worlds Finest",
    "issue": 7,
    "price": "$2.99",
    "publisher": "DC",
    "count": 32010
  },
  {
    "id": "talon-dc",
    "rank": 68,
    "title": "Talon",
    "issue": 3,
    "price": "$2.99",
    "publisher": "DC",
    "count": 31531
  },
  {
    "id": "deathmatch-boom",
    "rank": 69,
    "title": "Deathmatch",
    "issue": 1,
    "price": "$1.00",
    "publisher": "Boom",
    "count": 30946
  },
  {
    "id": "supergirl-dc",
    "rank": 70,
    "title": "Supergirl",
    "issue": 15,
    "price": "$2.99",
    "publisher": "DC",
    "count": 30814
  },
  {
    "id": "secret-avengers-marvel",
    "rank": 71,
    "title": "Secret Avengers",
    "issue": 35,
    "price": "$3.99",
    "publisher": "Marvel",
    "count": 30755
  },
  {
    "id": "x-men-marvel",
    "rank": 72,
    "title": "X-Men",
    "issue": 39,
    "price": "$3.99",
    "publisher": "Marvel",
    "count": 29326
  },
  {
    "id": "daredevil-end-of-days-marvel",
    "rank": 73,
    "title": "Daredevil End of Days",
    "issue": 3,
    "price": "$3.99",
    "publisher": "Marvel",
    "count": 29273
  },
  {
    "id": "happy-image",
    "rank": 74,
    "title": "Happy",
    "issue": 3,
    "price": "$2.99",
    "publisher": "Image",
    "count": 28767
  },
  {
    "id": "avenging-spider-man-marvel",
    "rank": 75,
    "title": "Avenging Spider-Man",
    "issue": 15,
    "price": "$3.99",
    "publisher": "Marvel",
    "count": 28240
  },
  {
    "id": "hellboy-in-hell-dark-horse",
    "rank": 76,
    "title": "Hellboy In Hell",
    "issue": 1,
    "price": "$2.99",
    "publisher": "Dark Horse",
    "count": 28096
  },
  {
    "id": "justice-league-dark-dc",
    "rank": 77,
    "title": "Justice League Dark",
    "issue": 15,
    "price": "$2.99",
    "publisher": "DC",
    "count": 27712
  },
  {
    "id": "ultimate-comics-ultimates-marvel",
    "rank": 78,
    "title": "Ultimate Comics Ultimates",
    "issue": 18,
    "price": "$2.99",
    "publisher": "Marvel",
    "count": 27659
  },
  {
    "id": "superboy-dc",
    "rank": 79,
    "title": "Superboy",
    "issue": 15,
    "price": "$2.99",
    "publisher": "DC",
    "count": 27619
  },
  {
    "id": "ultimate-comics-ultimates-marvel",
    "rank": 80,
    "title": "Ultimate Comics Ultimates",
    "issue": 19,
    "price": "$3.99",
    "publisher": "Marvel",
    "count": 26971
  },
  {
    "id": "scarlet-spider-marvel",
    "rank": 81,
    "title": "Scarlet Spider",
    "issue": 12,
    "price": "$2.99",
    "publisher": "Marvel",
    "count": 26652
  },
  {
    "id": "astonishing-x-men-marvel",
    "rank": 82,
    "title": "Astonishing X-Men",
    "issue": 57,
    "price": "$3.99",
    "publisher": "Marvel",
    "count": 26263
  },
  {
    "id": "scarlet-spider-marvel",
    "rank": 83,
    "title": "Scarlet Spider",
    "issue": 12,
    "price": "$2.99",
    "publisher": "Marvel",
    "count": 25771
  },
  {
    "id": "legends-of-the-dark-knight-dc",
    "rank": 84,
    "title": "Legends of the Dark Knight",
    "issue": 3,
    "price": "$3.99",
    "publisher": "DC",
    "count": 25710
  },
  {
    "id": "venom-marvel",
    "rank": 85,
    "title": "Venom",
    "issue": 28,
    "price": "$2.99",
    "publisher": "Marvel",
    "count": 25573
  },
  {
    "id": "punisher-war-zone-marvel",
    "rank": 86,
    "title": "Punisher War Zone",
    "issue": 2,
    "price": "$2.99",
    "publisher": "Marvel",
    "count": 25471
  },
  {
    "id": "ultimate-comics-x-men-marvel",
    "rank": 87,
    "title": "Ultimate Comics X-Men",
    "issue": 20,
    "price": "$3.99",
    "publisher": "Marvel",
    "count": 24789
  },
  {
    "id": "birds-of-prey-dc",
    "rank": 88,
    "title": "Birds of Prey",
    "issue": 15,
    "price": "$2.99",
    "publisher": "DC",
    "count": 24026
  },
  {
    "id": "gambit-marvel",
    "rank": 89,
    "title": "Gambit",
    "issue": 7,
    "price": "$2.99",
    "publisher": "Marvel",
    "count": 23978
  },
  {
    "id": "winter-soldier-marvel",
    "rank": 90,
    "title": "Winter Soldier",
    "issue": 13,
    "price": "$2.99",
    "publisher": "Marvel",
    "count": 23951
  },
  {
    "id": "buffy-the-vampire-slayer-season-9-freefall-dark-horse",
    "rank": 91,
    "title": "Buffy the Vampire Slayer Season 9 Freefall",
    "issue": 16,
    "price": "$2.99",
    "publisher": "Dark Horse",
    "count": 23896
  },
  {
    "id": "journey-into-mystery-marvel",
    "rank": 92,
    "title": "Journey Into Mystery",
    "issue": 647,
    "price": "$2.99",
    "publisher": "Marvel",
    "count": 22514
  },
  {
    "id": "x-factor-marvel",
    "rank": 93,
    "title": "X-Factor",
    "issue": 248,
    "price": "$2.99",
    "publisher": "Marvel",
    "count": 21664
  },
  {
    "id": "jsa-liberty-files-the-whistling-skull-dc",
    "rank": 94,
    "title": "Jsa Liberty Files The Whistling Skull",
    "issue": 1,
    "price": "$2.99",
    "publisher": "DC",
    "count": 21370
  },
  {
    "id": "x-factor-marvel",
    "rank": 95,
    "title": "X-Factor",
    "issue": 249,
    "price": "$2.99",
    "publisher": "Marvel",
    "count": 21211
  },
  {
    "id": "phantom-stranger-dc",
    "rank": 96,
    "title": "Phantom Stranger",
    "issue": 3,
    "price": "$2.99",
    "publisher": "DC",
    "count": 21040
  },
  {
    "id": "hellboy-in-hell-dark-horse",
    "rank": 97,
    "title": "Hellboy In Hell",
    "issue": 2,
    "price": "$2.99",
    "publisher": "Dark Horse",
    "count": 21010
  },
  {
    "id": "red-she-hulk-marvel",
    "rank": 98,
    "title": "Red She-Hulk",
    "issue": 60,
    "price": "$2.99",
    "publisher": "Marvel",
    "count": 20798
  },
  {
    "id": "green-arrow-dc",
    "rank": 99,
    "title": "Green Arrow",
    "issue": 15,
    "price": "$2.99",
    "publisher": "DC",
    "count": 20672
  },
  {
    "id": "dark-avengers-marvel",
    "rank": 100,
    "title": "Dark Avengers",
    "issue": 184,
    "price": "$2.99",
    "publisher": "Marvel",
    "count": 20584
  },
  {
    "id": "star-trek-tng-doctor-who-assimilation-idw",
    "rank": 101,
    "title": "Star Trek Tng Doctor Who Assimilation",
    "issue": 8,
    "price": "$3.99",
    "publisher": "IDW",
    "count": 20553
  },
  {
    "id": "adventure-time-fionna-cake-boom",
    "rank": 102,
    "title": "Adventure Time Fionna & Cake",
    "issue": 1,
    "price": "$3.99",
    "publisher": "Boom",
    "count": 20290
  },
  {
    "id": "captain-marvel-marvel",
    "rank": 103,
    "title": "Captain Marvel",
    "issue": 8,
    "price": "$2.99",
    "publisher": "Marvel",
    "count": 19970
  },
  {
    "id": "marvel-universe-vs-avengers-marvel",
    "rank": 104,
    "title": "Marvel Universe Vs Avengers",
    "issue": 3,
    "price": "$3.99",
    "publisher": "Marvel",
    "count": 19355
  },
  {
    "id": "age-of-apocalypse-marvel",
    "rank": 105,
    "title": "Age of Apocalypse",
    "issue": 10,
    "price": "$2.99",
    "publisher": "Marvel",
    "count": 19337
  },
  {
    "id": "all-star-western-dc",
    "rank": 106,
    "title": "All Star Western",
    "issue": 15,
    "price": "$3.99",
    "publisher": "DC",
    "count": 19190
  },
  {
    "id": "ultimate-comics-iron-man-marvel",
    "rank": 107,
    "title": "Ultimate Comics Iron Man",
    "issue": 3,
    "price": "$3.99",
    "publisher": "Marvel",
    "count": 18992
  },
  {
    "id": "smallville-season-11-dc",
    "rank": 108,
    "title": "Smallville Season 11",
    "issue": 8,
    "price": "$3.99",
    "publisher": "DC",
    "count": 18633
  },
  {
    "id": "mara-image",
    "rank": 109,
    "title": "Mara",
    "issue": 1,
    "price": "$2.99",
    "publisher": "Image",
    "count": 18164
  },
  {
    "id": "batman-beyond-unlimited-dc",
    "rank": 110,
    "title": "Batman Beyond Unlimited",
    "issue": 11,
    "price": "$3.99",
    "publisher": "DC",
    "count": 18089
  },
  {
    "id": "fatale-image",
    "rank": 111,
    "title": "Fatale",
    "issue": 11,
    "price": "$3.50",
    "publisher": "Image",
    "count": 18055
  },
  {
    "id": "batman-arkham-unhinged-dc",
    "rank": 112,
    "title": "Batman Arkham Unhinged",
    "issue": 9,
    "price": "$2.99",
    "publisher": "DC",
    "count": 17220
  },
  {
    "id": "manhattan-projects-image",
    "rank": 113,
    "title": "Manhattan Projects",
    "issue": 8,
    "price": "$3.50",
    "publisher": "Image",
    "count": 17028
  },
  {
    "id": "masks-dynamic-forces",
    "rank": 114,
    "title": "Masks",
    "issue": 2,
    "price": "$3.99",
    "publisher": "Dynamic Forces",
    "count": 16923
  },
  {
    "id": "fairest-dc",
    "rank": 115,
    "title": "Fairest",
    "issue": 10,
    "price": "$2.99",
    "publisher": "DC",
    "count": 16919
  },
  {
    "id": "shadowman-valiant",
    "rank": 116,
    "title": "Shadowman",
    "issue": 2,
    "price": "$3.99",
    "publisher": "Valiant",
    "count": 16917
  },
  {
    "id": "legion-of-super-heroes-dc",
    "rank": 117,
    "title": "Legion of Super Heroes",
    "issue": 15,
    "price": "$2.99",
    "publisher": "DC",
    "count": 16912
  },
  {
    "id": "he-man-and-the-masters-of-the-universe-dc",
    "rank": 118,
    "title": "He Man And The Masters of the Universe",
    "issue": 5,
    "price": "$2.99",
    "publisher": "DC",
    "count": 16858
  },
  {
    "id": "teenage-mutant-ninja-turtles-idw",
    "rank": 119,
    "title": "Teenage Mutant Ninja Turtles",
    "issue": 17,
    "price": "$3.99",
    "publisher": "IDW",
    "count": 16703
  },
  {
    "id": "x-treme-x-men-marvel",
    "rank": 120,
    "title": "X-Treme X-Men",
    "issue": 7,
    "price": "$2.99",
    "publisher": "Marvel",
    "count": 16682
  },
  {
    "id": "adventure-time-marceline-scream-queens-boom",
    "rank": 121,
    "title": "Adventure Time Marceline Scream Queens",
    "issue": 6,
    "price": "$3.99",
    "publisher": "Boom",
    "count": 16624
  },
  {
    "id": "x-treme-x-men-marvel",
    "rank": 122,
    "title": "X-Treme X-Men",
    "issue": 8,
    "price": "$2.99",
    "publisher": "Marvel",
    "count": 16536
  },
  {
    "id": "captain-america-and-black-widow-marvel",
    "rank": 123,
    "title": "Captain America And Black Widow",
    "issue": 640,
    "price": "$2.99",
    "publisher": "Marvel",
    "count": 16530
  },
  {
    "id": "buffy-the-vampire-slayer-willow-wonderland-dark-horse",
    "rank": 124,
    "title": "Buffy The Vampire Slayer Willow Wonderland",
    "issue": 2,
    "price": "$2.99",
    "publisher": "Dark Horse",
    "count": 16401
  },
  {
    "id": "image-firsts-walking-dead-image",
    "rank": 125,
    "title": "Image Firsts Walking Dead",
    "issue": 1,
    "price": "$1.00",
    "publisher": "Image",
    "count": 16253
  },
  {
    "id": "dial-h-dc",
    "rank": 126,
    "title": "Dial H",
    "issue": 7,
    "price": "$2.99",
    "publisher": "DC",
    "count": 16217
  },
  {
    "id": "ravagers-dc",
    "rank": 127,
    "title": "Ravagers",
    "issue": 7,
    "price": "$2.99",
    "publisher": "DC",
    "count": 16177
  },
  {
    "id": "invincible-image",
    "rank": 128,
    "title": "Invincible",
    "issue": 98,
    "price": "$2.99",
    "publisher": "Image",
    "count": 16139
  },
  {
    "id": "fables-dc",
    "rank": 129,
    "title": "Fables",
    "issue": 124,
    "price": "$2.99",
    "publisher": "DC",
    "count": 16018
  },
  {
    "id": "arrow-dc",
    "rank": 130,
    "title": "Arrow",
    "issue": 2,
    "price": "$3.99",
    "publisher": "DC",
    "count": 15780
  },
  {
    "id": "frankenstein-agent-of-shade-dc",
    "rank": 131,
    "title": "Frankenstein Agent of Shade",
    "issue": 15,
    "price": "$2.99",
    "publisher": "DC",
    "count": 15705
  },
  {
    "id": "thief-of-thieves-image",
    "rank": 132,
    "title": "Thief of Thieves",
    "issue": 11,
    "price": "$2.99",
    "publisher": "Image",
    "count": 15605
  },
  {
    "id": "buffy-the-vampire-slayer-willow-wonderland-dark-horse",
    "rank": 133,
    "title": "Buffy The Vampire Slayer Willow Wonderland",
    "issue": 3,
    "price": "$2.99",
    "publisher": "Dark Horse",
    "count": 15584
  },
  {
    "id": "invincible-image",
    "rank": 134,
    "title": "Invincible",
    "issue": 99,
    "price": "$2.99",
    "publisher": "Image",
    "count": 15566
  },
  {
    "id": "star-wars-purge-tyrants-fist-dark-horse",
    "rank": 135,
    "title": "Star Wars Purge Tyrants Fist",
    "issue": 1,
    "price": "$3.50",
    "publisher": "Dark Horse",
    "count": 15546
  },
  {
    "id": "stormwatch-dc",
    "rank": 136,
    "title": "Stormwatch",
    "issue": 15,
    "price": "$2.99",
    "publisher": "DC",
    "count": 15437
  },
  {
    "id": "team-7-dc",
    "rank": 137,
    "title": "Team 7",
    "issue": 3,
    "price": "$2.99",
    "publisher": "DC",
    "count": 15381
  },
  {
    "id": "demon-knights-dc",
    "rank": 138,
    "title": "Demon Knights",
    "issue": 15,
    "price": "$2.99",
    "publisher": "DC",
    "count": 15152
  },
  {
    "id": "angel-faith-dark-horse",
    "rank": 139,
    "title": "Angel & Faith",
    "issue": 17,
    "price": "$2.99",
    "publisher": "Dark Horse",
    "count": 15026
  },
  {
    "id": "vampirella-strikes-dynamic-forces",
    "rank": 140,
    "title": "Vampirella Strikes",
    "issue": 1,
    "price": "$3.99",
    "publisher": "Dynamic Forces",
    "count": 14862
  },
  {
    "id": "batwing-dc",
    "rank": 141,
    "title": "Batwing",
    "issue": 15,
    "price": "$2.99",
    "publisher": "DC",
    "count": 14674
  },
  {
    "id": "star-wars-dawn-of-the-jedi-prisoner-of-bogan-dark-horse",
    "rank": 142,
    "title": "Star Wars Dawn of the Jedi Prisoner of Bogan",
    "issue": 2,
    "price": "$2.99",
    "publisher": "Dark Horse",
    "count": 14588
  },
  {
    "id": "archer-armstrong-valiant",
    "rank": 143,
    "title": "Archer & Armstrong",
    "issue": 5,
    "price": "$3.99",
    "publisher": "Valiant",
    "count": 14544
  },
  {
    "id": "x-o-manowar-valiant",
    "rank": 144,
    "title": "X-O Manowar",
    "issue": 8,
    "price": "$3.99",
    "publisher": "Valiant",
    "count": 14462
  },
  {
    "id": "fury-max-marvel",
    "rank": 145,
    "title": "Fury Max",
    "issue": 7,
    "price": "$3.99",
    "publisher": "Marvel",
    "count": 14345
  },
  {
    "id": "legion-lost-dc",
    "rank": 146,
    "title": "Legion Lost",
    "issue": 15,
    "price": "$2.99",
    "publisher": "DC",
    "count": 14005
  },
  {
    "id": "judge-dredd-idw",
    "rank": 147,
    "title": "Judge Dredd",
    "issue": 2,
    "price": "$3.99",
    "publisher": "IDW",
    "count": 13995
  },
  {
    "id": "sword-of-sorcery-dc",
    "rank": 148,
    "title": "Sword of Sorcery",
    "issue": 3,
    "price": "$3.99",
    "publisher": "DC",
    "count": 13752
  },
  {
    "id": "savage-hawkman-dc",
    "rank": 149,
    "title": "Savage Hawkman",
    "issue": 15,
    "price": "$2.99",
    "publisher": "DC",
    "count": 13564
  },
  {
    "id": "deathstroke-dc",
    "rank": 150,
    "title": "Deathstroke",
    "issue": 15,
    "price": "$2.99",
    "publisher": "DC",
    "count": 13528
  },
  {
    "id": "conan-the-barbarian-dark-horse",
    "rank": 151,
    "title": "Conan The Barbarian",
    "issue": 11,
    "price": "$3.50",
    "publisher": "Dark Horse",
    "count": 13436
  },
  {
    "id": "star-wars-purge-tyrants-fist-dark-horse",
    "rank": 152,
    "title": "Star Wars Purge Tyrants Fist",
    "issue": 2,
    "price": "$3.50",
    "publisher": "Dark Horse",
    "count": 13429
  },
  {
    "id": "american-vampire-dc",
    "rank": 153,
    "title": "American Vampire",
    "issue": 34,
    "price": "$2.99",
    "publisher": "DC",
    "count": 13416
  },
  {
    "id": "ame-comi-girls-dc",
    "rank": 154,
    "title": "Ame Comi Girls",
    "issue": 3,
    "price": "$3.99",
    "publisher": "DC",
    "count": 13185
  },
  {
    "id": "i-vampire-dc",
    "rank": 155,
    "title": "I Vampire",
    "issue": 15,
    "price": "$2.99",
    "publisher": "DC",
    "count": 12846
  },
  {
    "id": "harbinger-valiant",
    "rank": 156,
    "title": "Harbinger",
    "issue": 7,
    "price": "$3.99",
    "publisher": "Valiant",
    "count": 12783
  },
  {
    "id": "dc-universe-presents-dc",
    "rank": 157,
    "title": "DC Universe Presents",
    "issue": 15,
    "price": "$2.99",
    "publisher": "DC",
    "count": 12561
  },
  {
    "id": "bloodshot-valiant",
    "rank": 158,
    "title": "Bloodshot",
    "issue": 6,
    "price": "$3.99",
    "publisher": "Valiant",
    "count": 12508
  },
  {
    "id": "legend-of-luther-strode-image",
    "rank": 159,
    "title": "Legend of Luther Strode",
    "issue": 1,
    "price": "$3.50",
    "publisher": "Image",
    "count": 12433
  },
  {
    "id": "fury-of-firestorm-the-nuclear-men-dc",
    "rank": 160,
    "title": "Fury of Firestorm The Nuclear Men",
    "issue": 15,
    "price": "$2.99",
    "publisher": "DC",
    "count": 11997
  },
  {
    "id": "django-unchained-dc",
    "rank": 161,
    "title": "Django Unchained",
    "issue": 1,
    "price": "$3.99",
    "publisher": "DC",
    "count": 11795
  },
  {
    "id": "punk-rock-jesus-dc",
    "rank": 162,
    "title": "Punk Rock Jesus",
    "issue": 6,
    "price": "$2.99",
    "publisher": "DC",
    "count": 11746
  },
  {
    "id": "blue-beetle-dc",
    "rank": 163,
    "title": "Blue Beetle",
    "issue": 15,
    "price": "$2.99",
    "publisher": "DC",
    "count": 11744
  },
  {
    "id": "great-pacific-image",
    "rank": 164,
    "title": "Great Pacific",
    "issue": 2,
    "price": "$2.99",
    "publisher": "Image",
    "count": 11740
  },
  {
    "id": "star-wars-lost-tribe-of-the-sith-dark-horse",
    "rank": 165,
    "title": "Star Wars Lost Tribe of the Sith",
    "issue": 5,
    "price": "$2.99",
    "publisher": "Dark Horse",
    "count": 11567
  },
  {
    "id": "masks-dynamic-forces",
    "rank": 166,
    "title": "Masks",
    "issue": 1,
    "price": "$3.99",
    "publisher": "Dynamic Forces",
    "count": 11560
  },
  {
    "id": "magic-the-gathering-path-of-vengeance-idw",
    "rank": 167,
    "title": "Magic The Gathering Path of Vengeance",
    "issue": 1,
    "price": "$4.99",
    "publisher": "IDW",
    "count": 11412
  },
  {
    "id": "star-wars-agent-of-the-empire-hard-targets-dark-horse",
    "rank": 168,
    "title": "Star Wars Agent of the Empire Hard Targets",
    "issue": 3,
    "price": "$2.99",
    "publisher": "Dark Horse",
    "count": 11391
  },
  {
    "id": "americas-got-powers-image",
    "rank": 169,
    "title": "Americas Got Powers",
    "issue": 4,
    "price": "$2.99",
    "publisher": "Image",
    "count": 11291
  },
  {
    "id": "doctor-who-vol-3-idw",
    "rank": 170,
    "title": "Doctor Who Vol. 3",
    "issue": 3,
    "price": "$3.99",
    "publisher": "IDW",
    "count": 11277
  },
  {
    "id": "human-bomb-dc",
    "rank": 171,
    "title": "Human Bomb",
    "issue": 1,
    "price": "$2.99",
    "publisher": "DC",
    "count": 11212
  },
  {
    "id": "clone-image",
    "rank": 172,
    "title": "Clone",
    "issue": 2,
    "price": "$2.99",
    "publisher": "Image",
    "count": 11144
  },
  {
    "id": "grifter-dc",
    "rank": 173,
    "title": "Grifter",
    "issue": 15,
    "price": "$2.99",
    "publisher": "DC",
    "count": 10923
  },
  {
    "id": "massive-dark-horse",
    "rank": 174,
    "title": "Massive",
    "issue": 7,
    "price": "$3.50",
    "publisher": "Dark Horse",
    "count": 10854
  },
  {
    "id": "image-firsts-saga-image",
    "rank": 175,
    "title": "Image Firsts Saga",
    "issue": 1,
    "price": "$1.00",
    "publisher": "Image",
    "count": 10536
  },
  {
    "id": "danger-girl-gi-joe-idw",
    "rank": 176,
    "title": "Danger Girl G.I. Joe",
    "issue": 5,
    "price": "$3.99",
    "publisher": "IDW",
    "count": 10454
  },
  {
    "id": "bprd-1948-dark-horse",
    "rank": 177,
    "title": "BPRD 1948",
    "issue": 3,
    "price": "$3.50",
    "publisher": "Dark Horse",
    "count": 10452
  },
  {
    "id": "locke-key-omega-idw",
    "rank": 178,
    "title": "Locke & Key Omega",
    "issue": 2,
    "price": "$3.99",
    "publisher": "IDW",
    "count": 10244
  },
  {
    "id": "bravest-warriors-boom",
    "rank": 179,
    "title": "Bravest Warriors",
    "issue": 3,
    "price": "$3.99",
    "publisher": "Boom",
    "count": 10229
  },
  {
    "id": "bprd-hell-on-earth-dark-horse",
    "rank": 180,
    "title": "BPRD Hell On Earth",
    "issue": 102,
    "price": "$3.50",
    "publisher": "Dark Horse",
    "count": 10169
  },
  {
    "id": "transformers-robots-in-disguise-idw",
    "rank": 181,
    "title": "Transformers Robots In Disguise",
    "issue": 12,
    "price": "$3.99",
    "publisher": "IDW",
    "count": 10161
  },
  {
    "id": "star-trek-next-generation-hive-idw",
    "rank": 182,
    "title": "Star Trek Next Generation Hive",
    "issue": 3,
    "price": "$3.99",
    "publisher": "IDW",
    "count": 10097
  },
  {
    "id": "transformers-more-than-meets-eye-idw",
    "rank": 183,
    "title": "Transformers More Than Meets Eye",
    "issue": 12,
    "price": "$3.99",
    "publisher": "IDW",
    "count": 10076
  },
  {
    "id": "transformers-regeneration-one-idw",
    "rank": 184,
    "title": "Transformers Regeneration One",
    "issue": 86,
    "price": "$3.99",
    "publisher": "IDW",
    "count": 10037
  },
  {
    "id": "star-trek-idw",
    "rank": 185,
    "title": "Star Trek",
    "issue": 16,
    "price": "$3.99",
    "publisher": "IDW",
    "count": 9990
  },
  {
    "id": "blackacre-image",
    "rank": 186,
    "title": "Blackacre",
    "issue": 1,
    "price": "$2.99",
    "publisher": "Image",
    "count": 9804
  },
  {
    "id": "great-pacific-image",
    "rank": 187,
    "title": "Great Pacific",
    "issue": 3,
    "price": "$2.99",
    "publisher": "Image",
    "count": 9608
  },
  {
    "id": "shadow-special-dynamic-forces",
    "rank": 188,
    "title": "Shadow Special",
    "issue": 1,
    "price": "$4.99",
    "publisher": "Dynamic Forces",
    "count": 9536
  },
  {
    "id": "hollows-idw",
    "rank": 189,
    "title": "Hollows",
    "issue": 1,
    "price": "$3.99",
    "publisher": "IDW",
    "count": 9303
  },
  {
    "id": "hellblazer-dc",
    "rank": 190,
    "title": "Hellblazer",
    "issue": 298,
    "price": "$2.99",
    "publisher": "DC",
    "count": 9132
  },
  {
    "id": "godzilla-half-century-war-idw",
    "rank": 192,
    "title": "Godzilla Half Century War",
    "issue": 4,
    "price": "$3.99",
    "publisher": "IDW",
    "count": 9090
  },
  {
    "id": "gi-combat-dc",
    "rank": 193,
    "title": "G.I. Combat",
    "issue": 7,
    "price": "$3.99",
    "publisher": "DC",
    "count": 8941
  },
  {
    "id": "joe-kubert-presents-dc",
    "rank": 194,
    "title": "Joe Kubert Presents",
    "issue": 3,
    "price": "$4.99",
    "publisher": "DC",
    "count": 8897
  },
  {
    "id": "sonic-the-hedgehog-archie",
    "rank": 195,
    "title": "Sonic The Hedgehog",
    "issue": 243,
    "price": "$2.99",
    "publisher": "Archie",
    "count": 8760
  },
  {
    "id": "crossed-badlands-avatar",
    "rank": 196,
    "title": "Crossed Badlands",
    "issue": 19,
    "price": "$3.99",
    "publisher": "Avatar",
    "count": 8655
  },
  {
    "id": "warlord-of-mars-dejah-thoris-dynamic-forces",
    "rank": 197,
    "title": "Warlord of Mars Dejah Thoris",
    "issue": 19,
    "price": "$3.99",
    "publisher": "Dynamic Forces",
    "count": 8538
  },
  {
    "id": "unwritten-dc",
    "rank": 198,
    "title": "Unwritten",
    "issue": 44,
    "price": "$2.99",
    "publisher": "DC",
    "count": 8532
  },
  {
    "id": "crossed-badlands-avatar",
    "rank": 199,
    "title": "Crossed Badlands",
    "issue": 20,
    "price": "$3.99",
    "publisher": "Avatar",
    "count": 8461
  },
  {
    "id": "transformers-prime-rage-of-the-dinobots-idw",
    "rank": 200,
    "title": "Transformers Prime Rage of the Dinobots",
    "issue": 2,
    "price": "$3.99",
    "publisher": "IDW",
    "count": 8284
  },
  {
    "id": "witchblade-image",
    "rank": 201,
    "title": "Witchblade",
    "issue": 162,
    "price": "$2.99",
    "publisher": "Image",
    "count": 8098
  },
  {
    "id": "i-love-trouble-image",
    "rank": 202,
    "title": "I Love Trouble",
    "issue": 1,
    "price": "$2.99",
    "publisher": "Image",
    "count": 7974
  },
  {
    "id": "crow-skinning-the-wolves-idw",
    "rank": 203,
    "title": "Crow Skinning The Wolves",
    "issue": 1,
    "price": "$3.99",
    "publisher": "IDW",
    "count": 7883
  },
  {
    "id": "evil-ernie-dynamic-forces",
    "rank": 204,
    "title": "Evil Ernie",
    "issue": 3,
    "price": "$3.99",
    "publisher": "Dynamic Forces",
    "count": 7832
  },
  {
    "id": "rachel-rising-abstract",
    "rank": 205,
    "title": "Rachel Rising",
    "issue": 13,
    "price": "$3.99",
    "publisher": "Abstract",
    "count": 7782
  },
  {
    "id": "gi-joe-a-real-american-hero-idw",
    "rank": 206,
    "title": "G.I. Joe A Real American Hero",
    "issue": 185,
    "price": "$3.99",
    "publisher": "IDW",
    "count": 7777
  },
  {
    "id": "gi-joe-vol-2-idw",
    "rank": 208,
    "title": "G.I. Joe Vol. 2",
    "issue": 20,
    "price": "$3.99",
    "publisher": "IDW",
    "count": 7575
  },
  {
    "id": "warlord-of-mars-dejah-thoris-dynamic-forces",
    "rank": 209,
    "title": "Warlord of Mars Dejah Thoris",
    "issue": 20,
    "price": "$3.99",
    "publisher": "Dynamic Forces",
    "count": 7555
  },
  {
    "id": "lot-13-dc",
    "rank": 210,
    "title": "Lot 13",
    "issue": 3,
    "price": "$2.99",
    "publisher": "DC",
    "count": 7551
  },
  {
    "id": "superman-family-adventures-dc",
    "rank": 211,
    "title": "Superman Family Adventures",
    "issue": 8,
    "price": "$2.99",
    "publisher": "DC",
    "count": 7487
  },
  {
    "id": "nowhere-men-image",
    "rank": 213,
    "title": "Nowhere Men",
    "issue": 2,
    "price": "$2.99",
    "publisher": "Image",
    "count": 7368
  },
  {
    "id": "haunt-image",
    "rank": 214,
    "title": "Haunt",
    "issue": 28,
    "price": "$2.99",
    "publisher": "Image",
    "count": 7327
  },
  {
    "id": "vampirella-dynamic-forces",
    "rank": 215,
    "title": "Vampirella",
    "issue": 25,
    "price": "$3.99",
    "publisher": "Dynamic Forces",
    "count": 7293
  },
  {
    "id": "wonderland-zenescope",
    "rank": 216,
    "title": "Wonderland",
    "issue": 6,
    "price": "$2.99",
    "publisher": "Zenescope",
    "count": 7242
  },
  {
    "id": "young-justice-dc",
    "rank": 217,
    "title": "Young Justice",
    "issue": 23,
    "price": "$2.99",
    "publisher": "DC",
    "count": 7200
  },
  {
    "id": "spongebob-comics-united-plankton",
    "rank": 218,
    "title": "Spongebob Comics",
    "issue": 15,
    "price": "$2.99",
    "publisher": "United Plankton",
    "count": 7196
  },
  {
    "id": "castle-a-calm-before-storm-marvel",
    "rank": 219,
    "title": "Castle A Calm Before Storm",
    "issue": 1,
    "price": "$3.99",
    "publisher": "Marvel",
    "count": 7174
  },
  {
    "id": "robyn-hood-zenescope",
    "rank": 220,
    "title": "Robyn Hood",
    "issue": 4,
    "price": "$2.99",
    "publisher": "Zenescope",
    "count": 7136
  },
  {
    "id": "black-kiss-ii-image",
    "rank": 221,
    "title": "Black Kiss II",
    "issue": 5,
    "price": "$2.99",
    "publisher": "Image",
    "count": 7044
  },
  {
    "id": "sonic-universe-archie",
    "rank": 223,
    "title": "Sonic Universe",
    "issue": 47,
    "price": "$2.99",
    "publisher": "Archie",
    "count": 6837
  },
  {
    "id": "ghostbusters-idw",
    "rank": 224,
    "title": "Ghostbusters",
    "issue": 16,
    "price": "$3.99",
    "publisher": "IDW",
    "count": 6813
  },
  {
    "id": "simpsons-comics-bongo",
    "rank": 225,
    "title": "Simpsons Comics",
    "issue": 197,
    "price": "$2.99",
    "publisher": "Bongo",
    "count": 6779
  },
  {
    "id": "lady-death-avatar",
    "rank": 226,
    "title": "Lady Death",
    "issue": 24,
    "price": "$3.99",
    "publisher": "Avatar",
    "count": 6762
  },
  {
    "id": "witch-doctor-malpractice-image",
    "rank": 227,
    "title": "Witch Doctor Malpractice",
    "issue": 2,
    "price": "$2.99",
    "publisher": "Image",
    "count": 6673
  },
  {
    "id": "snake-eyes-storm-shadow-idw",
    "rank": 228,
    "title": "Snake Eyes & Storm Shadow",
    "issue": 20,
    "price": "$3.99",
    "publisher": "IDW",
    "count": 6663
  },
  {
    "id": "my-little-pony-friendship-is-magic-idw",
    "rank": 229,
    "title": "My Little Pony Friendship Is Magic",
    "issue": 1,
    "price": "$3.99",
    "publisher": "IDW",
    "count": 6651
  },
  {
    "id": "fashion-beast-avatar",
    "rank": 230,
    "title": "Fashion Beast",
    "issue": 4,
    "price": "$3.99",
    "publisher": "Avatar",
    "count": 6639
  },
  {
    "id": "saucer-country-dc",
    "rank": 231,
    "title": "Saucer Country",
    "issue": 10,
    "price": "$2.99",
    "publisher": "DC",
    "count": 6608
  },
  {
    "id": "sherlock-holmes-liverpool-demon-dynamic-forces",
    "rank": 232,
    "title": "Sherlock Holmes Liverpool Demon",
    "issue": 1,
    "price": "$3.99",
    "publisher": "Dynamic Forces",
    "count": 6598
  },
  {
    "id": "cobra-idw",
    "rank": 233,
    "title": "Cobra",
    "issue": 20,
    "price": "$3.99",
    "publisher": "IDW",
    "count": 6589
  },
  {
    "id": "mars-attacks-idw",
    "rank": 234,
    "title": "Mars Attacks",
    "issue": 6,
    "price": "$3.99",
    "publisher": "IDW",
    "count": 6509
  },
  {
    "id": "grimm-fairy-tales-zenescope",
    "rank": 235,
    "title": "Grimm Fairy Tales",
    "issue": 80,
    "price": "$2.99",
    "publisher": "Zenescope",
    "count": 6508
  },
  {
    "id": "change-image",
    "rank": 237,
    "title": "Change",
    "issue": 1,
    "price": "$2.99",
    "publisher": "Image",
    "count": 6439
  },
  {
    "id": "mega-man-archie",
    "rank": 238,
    "title": "Mega Man",
    "issue": 20,
    "price": "$2.99",
    "publisher": "Archie",
    "count": 6351
  },
  {
    "id": "harvest-image",
    "rank": 239,
    "title": "Harvest",
    "issue": 5,
    "price": "$3.50",
    "publisher": "Image",
    "count": 6326
  },
  {
    "id": "image-firsts-thief-of-thieves-image",
    "rank": 240,
    "title": "Image Firsts Thief of Thieves",
    "issue": 1,
    "price": "$1.00",
    "publisher": "Image",
    "count": 6292
  },
  {
    "id": "lord-of-the-jungle-dynamic-forces",
    "rank": 241,
    "title": "Lord of the Jungle",
    "issue": 10,
    "price": "$3.99",
    "publisher": "Dynamic Forces",
    "count": 6259
  },
  {
    "id": "47-ronin-dark-horse",
    "rank": 242,
    "title": "47 Ronin",
    "issue": 2,
    "price": "$3.99",
    "publisher": "Dark Horse",
    "count": 6101
  },
  {
    "id": "youngblood-image",
    "rank": 243,
    "title": "Youngblood",
    "issue": 75,
    "price": "$4.99",
    "publisher": "Image",
    "count": 6049
  },
  {
    "id": "multiple-warheads-alphabet-to-infinity-image",
    "rank": 244,
    "title": "Multiple Warheads Alphabet To Infinity",
    "issue": 3,
    "price": "$2.99",
    "publisher": "Image",
    "count": 5981
  },
  {
    "id": "hack-slash-image",
    "rank": 245,
    "title": "Hack Slash",
    "issue": 21,
    "price": "$3.50",
    "publisher": "Image",
    "count": 5940
  },
  {
    "id": "garth-ennis-jennifer-blood-dynamic-forces",
    "rank": 246,
    "title": "Garth Ennis Jennifer Blood",
    "issue": 20,
    "price": "$3.99",
    "publisher": "Dynamic Forces",
    "count": 5933
  },
  {
    "id": "comeback-image",
    "rank": 247,
    "title": "Comeback",
    "issue": 2,
    "price": "$3.50",
    "publisher": "Image",
    "count": 5933
  },
  {
    "id": "red-sonja-dynamic-forces",
    "rank": 248,
    "title": "Red Sonja",
    "issue": 72,
    "price": "$3.99",
    "publisher": "Dynamic Forces",
    "count": 5856
  },
  {
    "id": "damsels-dynamic-forces",
    "rank": 249,
    "title": "Damsels",
    "issue": 4,
    "price": "$3.99",
    "publisher": "Dynamic Forces",
    "count": 5851
  },
  {
    "id": "grimm-fairy-tales-bad-girls-zenescope",
    "rank": 250,
    "title": "Grimm Fairy Tales Bad Girls",
    "issue": 5,
    "price": "$2.99",
    "publisher": "Zenescope",
    "count": 5822
  },
  {
    "id": "image-firsts-manhattan-projects-image",
    "rank": 251,
    "title": "Image Firsts Manhattan Projects",
    "issue": 1,
    "price": "$1.00",
    "publisher": "Image",
    "count": 5763
  },
  {
    "id": "artifacts-image",
    "rank": 252,
    "title": "Artifacts",
    "issue": 23,
    "price": "$3.99",
    "publisher": "Image",
    "count": 5708
  },
  {
    "id": "colder-dark-horse",
    "rank": 253,
    "title": "Colder",
    "issue": 2,
    "price": "$3.99",
    "publisher": "Dark Horse",
    "count": 5683
  },
  {
    "id": "prophet-image",
    "rank": 254,
    "title": "Prophet",
    "issue": 32,
    "price": "$3.99",
    "publisher": "Image",
    "count": 5642
  },
  {
    "id": "guarding-the-globe-image",
    "rank": 255,
    "title": "Guarding The Globe",
    "issue": 4,
    "price": "$2.99",
    "publisher": "Image",
    "count": 5628
  },
  {
    "id": "image-firsts-chew-image",
    "rank": 256,
    "title": "Image Firsts Chew",
    "issue": 1,
    "price": "$1.00",
    "publisher": "Image",
    "count": 5574
  },
  {
    "id": "the-spider-dynamic-forces",
    "rank": 257,
    "title": "The Spider",
    "issue": 7,
    "price": "$3.99",
    "publisher": "Dynamic Forces",
    "count": 5571
  },
  {
    "id": "suicide-squad-dc",
    "rank": 258,
    "title": "Suicide Squad",
    "issue": 14,
    "price": "$2.99",
    "publisher": "DC",
    "count": 5494
  },
  {
    "id": "green-lantern-the-animated-series-dc",
    "rank": 259,
    "title": "Green Lantern The Animated Series",
    "issue": 9,
    "price": "$2.99",
    "publisher": "DC",
    "count": 5464
  },
  {
    "id": "fathom-vol-4-aspen",
    "rank": 260,
    "title": "Fathom Vol. 4",
    "issue": 8,
    "price": "$3.50",
    "publisher": "Aspen",
    "count": 5414
  },
  {
    "id": "grimm-fairy-tales-sleepy-hollow-zenescope",
    "rank": 261,
    "title": "Grimm Fairy Tales Sleepy Hollow",
    "issue": 3,
    "price": "$2.99",
    "publisher": "Zenescope",
    "count": 5393
  },
  {
    "id": "to-hell-you-ride-dark-horse",
    "rank": 262,
    "title": "To Hell You Ride",
    "issue": 1,
    "price": "$3.99",
    "publisher": "Dark Horse",
    "count": 5382
  },
  {
    "id": "bart-simpson-comics-bongo",
    "rank": 263,
    "title": "Bart Simpson Comics",
    "issue": 78,
    "price": "$2.99",
    "publisher": "Bongo",
    "count": 5376
  },
  {
    "id": "image-firsts-fatale-image",
    "rank": 264,
    "title": "Image Firsts Fatale",
    "issue": 1,
    "price": "$1.00",
    "publisher": "Image",
    "count": 5330
  },
  {
    "id": "carbon-grey-vol-2-image",
    "rank": 265,
    "title": "Carbon Grey Vol. 2",
    "issue": 2,
    "price": "$3.99",
    "publisher": "Image",
    "count": 5302
  },
  {
    "id": "blackacre-image",
    "rank": 266,
    "title": "Blackacre",
    "issue": 2,
    "price": "$2.99",
    "publisher": "Image",
    "count": 5292
  },
  {
    "id": "queen-sonja-dynamic-forces",
    "rank": 267,
    "title": "Queen Sonja",
    "issue": 33,
    "price": "$3.99",
    "publisher": "Dynamic Forces",
    "count": 5269
  },
  {
    "id": "grimm-fairy-tales-myths-legends-zenescope",
    "rank": 268,
    "title": "Grimm Fairy Tales Myths & Legends",
    "issue": 24,
    "price": "$2.99",
    "publisher": "Zenescope",
    "count": 5269
  },
  {
    "id": "marvel-universe-ultimate-spider-man-marvel",
    "rank": 269,
    "title": "Marvel Universe Ultimate Spider-Man",
    "issue": 9,
    "price": "$2.99",
    "publisher": "Marvel",
    "count": 5235
  },
  {
    "id": "colder-dark-horse",
    "rank": 270,
    "title": "Colder",
    "issue": 3,
    "price": "$3.99",
    "publisher": "Dark Horse",
    "count": 5217
  },
  {
    "id": "green-hornet-dynamic-forces",
    "rank": 271,
    "title": "Green Hornet",
    "issue": 32,
    "price": "$3.99",
    "publisher": "Dynamic Forces",
    "count": 5217
  },
  {
    "id": "the-lone-ranger-dynamic-forces",
    "rank": 272,
    "title": "The Lone Ranger",
    "issue": 11,
    "price": "$3.99",
    "publisher": "Dynamic Forces",
    "count": 5216
  },
  {
    "id": "marvel-universe-avengers-earths-heroes-marvel",
    "rank": 273,
    "title": "Marvel Universe Avengers Earths Heroes",
    "issue": 9,
    "price": "$2.99",
    "publisher": "Marvel",
    "count": 5207
  },
  {
    "id": "flash-gordon-zeitgeist-dynamic-forces",
    "rank": 274,
    "title": "Flash Gordon Zeitgeist",
    "issue": 8,
    "price": "$3.99",
    "publisher": "Dynamic Forces",
    "count": 5182
  },
  {
    "id": "dark-horse-presents-dark-horse",
    "rank": 275,
    "title": "Dark Horse Presents",
    "issue": 19,
    "price": "$7.99",
    "publisher": "Dark Horse",
    "count": 5123
  },
  {
    "id": "caligula-heart-of-rome-avatar",
    "rank": 276,
    "title": "Caligula Heart of Rome",
    "issue": 1,
    "price": "$3.99",
    "publisher": "Avatar",
    "count": 5055
  },
  {
    "id": "ferals-avatar",
    "rank": 277,
    "title": "Ferals",
    "issue": 11,
    "price": "$3.99",
    "publisher": "Avatar",
    "count": 5045
  },
  {
    "id": "borderlands-origins-idw",
    "rank": 278,
    "title": "Borderlands Origins",
    "issue": 2,
    "price": "$3.99",
    "publisher": "IDW",
    "count": 5040
  },
  {
    "id": "simpsons-winter-wingding-bongo",
    "rank": 279,
    "title": "Simpsons Winter Wingding",
    "issue": 7,
    "price": "$4.99",
    "publisher": "Bongo",
    "count": 5012
  },
  {
    "id": "image-firsts-revival-image",
    "rank": 280,
    "title": "Image Firsts Revival",
    "issue": 1,
    "price": "$1.00",
    "publisher": "Image",
    "count": 5012
  },
  {
    "id": "battlefields-dynamic-forces",
    "rank": 281,
    "title": "Battlefields",
    "issue": 2,
    "price": "$3.99",
    "publisher": "Dynamic Forces",
    "count": 4966
  },
  {
    "id": "army-of-darkness-dynamic-forces",
    "rank": 282,
    "title": "Army of Darkness",
    "issue": 7,
    "price": "$3.99",
    "publisher": "Dynamic Forces",
    "count": 4963
  },
  {
    "id": "dark-shadows-vampirella-dynamic-forces",
    "rank": 283,
    "title": "Dark Shadows Vampirella",
    "issue": 5,
    "price": "$3.99",
    "publisher": "Dynamic Forces",
    "count": 4962
  },
  {
    "id": "darkness-image",
    "rank": 284,
    "title": "Darkness",
    "issue": 109,
    "price": "$2.99",
    "publisher": "Image",
    "count": 4961
  },
  {
    "id": "bionic-woman-dynamic-forces",
    "rank": 285,
    "title": "Bionic Woman",
    "issue": 6,
    "price": "$3.99",
    "publisher": "Dynamic Forces",
    "count": 4960
  },
  {
    "id": "creep-dark-horse",
    "rank": 286,
    "title": "Creep",
    "issue": 4,
    "price": "$3.50",
    "publisher": "Dark Horse",
    "count": 4951
  },
  {
    "id": "storm-dogs-image",
    "rank": 287,
    "title": "Storm Dogs",
    "issue": 2,
    "price": "$3.50",
    "publisher": "Image",
    "count": 4939
  },
  {
    "id": "hellraiser-road-below-boom",
    "rank": 288,
    "title": "Hellraiser Road Below",
    "issue": 3,
    "price": "$3.99",
    "publisher": "Boom",
    "count": 4921
  },
  {
    "id": "monsters-inc-marvel",
    "rank": 289,
    "title": "Monsters Inc",
    "issue": 1,
    "price": "$2.99",
    "publisher": "Marvel",
    "count": 4917
  },
  {
    "id": "freelancers-boom",
    "rank": 290,
    "title": "Freelancers",
    "issue": 2,
    "price": "$3.99",
    "publisher": "Boom",
    "count": 4904
  },
  {
    "id": "scooby-doo-where-are-you-dc",
    "rank": 291,
    "title": "Scooby Doo Where Are You",
    "issue": 28,
    "price": "$2.99",
    "publisher": "DC",
    "count": 4879
  },
  {
    "id": "popeye-idw",
    "rank": 292,
    "title": "Popeye",
    "issue": 8,
    "price": "$3.99",
    "publisher": "IDW",
    "count": 4866
  },
  {
    "id": "supurbia-boom",
    "rank": 293,
    "title": "Supurbia",
    "issue": 2,
    "price": "$3.99",
    "publisher": "Boom",
    "count": 4773
  },
  {
    "id": "soulfire-vol-4-aspen",
    "rank": 294,
    "title": "Soulfire Vol. 4",
    "issue": 3,
    "price": "$3.99",
    "publisher": "Aspen",
    "count": 4763
  },
  {
    "id": "i-love-trouble-image",
    "rank": 295,
    "title": "I Love Trouble",
    "issue": 2,
    "price": "$2.99",
    "publisher": "Image",
    "count": 4755
  },
  {
    "id": "simpsons-super-spectacular-bongo",
    "rank": 296,
    "title": "Simpsons Super Spectacular",
    "issue": 16,
    "price": "$2.99",
    "publisher": "Bongo",
    "count": 4739
  },
  {
    "id": "magic-the-gathering-spell-thief-idw",
    "rank": 297,
    "title": "Magic The Gathering Spell Thief",
    "issue": 3,
    "price": "$4.99",
    "publisher": "IDW",
    "count": 4710
  },
  {
    "id": "empowered-special-dark-horse",
    "rank": 298,
    "title": "Empowered Special",
    "issue": 3,
    "price": "$3.99",
    "publisher": "Dark Horse",
    "count": 4676
  },
  {
    "id": "dark-shadows-dynamic-forces",
    "rank": 299,
    "title": "Dark Shadows",
    "issue": 11,
    "price": "$3.99",
    "publisher": "Dynamic Forces",
    "count": 4661
  },
  {
    "id": "the-lone-ranger-snake-of-iron-dynamic-forces",
    "rank": 300,
    "title": "The Lone Ranger Snake of Iron",
    "issue": 4,
    "price": "$3.99",
    "publisher": "Dynamic Forces",
    "count": 4649
  },
  {
    "id": "stumptown-v2-oni",
    "rank": 309,
    "title": "Stumptown V2",
    "issue": 4,
    "price": "$3.99",
    "publisher": "Oni",
    "count": 4444
  },
  {
    "id": "executive-assistant-iris-vol-3-aspen",
    "rank": 315,
    "title": "Executive Assistant Iris Vol. 3",
    "issue": 1,
    "price": "$3.99",
    "publisher": "Aspen",
    "count": 4302
  },
  {
    "id": "lenore-volume-ii-titan",
    "rank": 316,
    "title": "Lenore Volume II",
    "issue": 7,
    "price": "$3.99",
    "publisher": "Titan",
    "count": 4283
  },
  {
    "id": "godstorm-zenescope",
    "rank": 320,
    "title": "Godstorm",
    "issue": 3,
    "price": "$2.99",
    "publisher": "Zenescope",
    "count": 4123
  },
  {
    "id": "executive-assistant-assassins-aspen",
    "rank": 326,
    "title": "Executive Assistant Assassins",
    "issue": 6,
    "price": "$3.99",
    "publisher": "Aspen",
    "count": 4014
  },
  {
    "id": "grimm-universe-zenescope",
    "rank": 331,
    "title": "Grimm Universe",
    "issue": 2,
    "price": "$3.99",
    "publisher": "Zenescope",
    "count": 3852
  },
  {
    "id": "atomic-robo-flying-she-devils-of-the-pacific-red-5",
    "rank": 332,
    "title": "Atomic Robo Flying She Devils of the Pacific",
    "issue": 5,
    "price": "$3.50",
    "publisher": "Red 5",
    "count": 3850
  },
  {
    "id": "kevin-keller-archie",
    "rank": 333,
    "title": "Kevin Keller",
    "issue": 6,
    "price": "$2.99",
    "publisher": "Archie",
    "count": 3834
  },
  {
    "id": "fly-vol-ii-zenescope",
    "rank": 335,
    "title": "Fly Vol. II",
    "issue": 2,
    "price": "$2.99",
    "publisher": "Zenescope",
    "count": 3800
  },
  {
    "id": "archie-archie",
    "rank": 345,
    "title": "Archie",
    "issue": 639,
    "price": "$2.99",
    "publisher": "Archie",
    "count": 3515
  },
  {
    "id": "idolized-aspen",
    "rank": 346,
    "title": "Idolized",
    "issue": 4,
    "price": "$3.99",
    "publisher": "Aspen",
    "count": 3451
  },
  {
    "id": "fly-vol-ii-zenescope",
    "rank": 347,
    "title": "Fly Vol. II",
    "issue": 3,
    "price": "$2.99",
    "publisher": "Zenescope",
    "count": 3446
  },
  {
    "id": "new-crusaders-rise-of-the-heroes-archie",
    "rank": 356,
    "title": "New Crusaders Rise of the Heroes",
    "issue": 4,
    "price": "$2.99",
    "publisher": "Archie",
    "count": 3011
  },
  {
    "id": "knights-of-the-dinner-table-kenzer",
    "rank": 357,
    "title": "Knights of the Dinner Table",
    "issue": 192,
    "price": "$5.99",
    "publisher": "Kenzer",
    "count": 2996
  },
  {
    "id": "knights-of-the-dinner-table-kenzer",
    "rank": 359,
    "title": "Knights of the Dinner Table",
    "issue": 193,
    "price": "$5.99",
    "publisher": "Kenzer",
    "count": 2945
  },
  {
    "id": "sixth-gun-oni",
    "rank": 363,
    "title": "Sixth Gun",
    "issue": 27,
    "price": "$3.99",
    "publisher": "Oni",
    "count": 2930
  },
  {
    "id": "wake-the-fck-up-zenescope",
    "rank": 370,
    "title": "Wake The F#Ck Up",
    "issue": 1,
    "price": "$2.99",
    "publisher": "Zenescope",
    "count": 2766
  },
  {
    "id": "courtney-crumrin-oni",
    "rank": 371,
    "title": "Courtney Crumrin",
    "issue": 8,
    "price": "$3.99",
    "publisher": "Oni",
    "count": 2724
  },
  {
    "id": "life-with-archie-archie",
    "rank": 374,
    "title": "Life With Archie",
    "issue": 25,
    "price": "$3.99",
    "publisher": "Archie",
    "count": 2542
  },
  {
    "id": "betty-veronica-archie",
    "rank": 381,
    "title": "Betty & Veronica",
    "issue": 263,
    "price": "$2.99",
    "publisher": "Archie",
    "count": 2328
  },
  {
    "id": "gold-digger-antarctic",
    "rank": 398,
    "title": "Gold Digger",
    "issue": 145,
    "price": "$3.99",
    "publisher": "Antarctic",
    "count": 1800
  },
  {
    "id": "joan-of-arc-from-the-ashes-big-dog",
    "rank": 401,
    "title": "Joan of Arc From The Ashes",
    "issue": 2,
    "price": "$3.50",
    "publisher": "Big Dog",
    "count": 1597
  },
  {
    "id": "victorian-secret-girls-of-steampunk-antarctic",
    "rank": 402,
    "title": "Victorian Secret Girls of Steampunk",
    "issue": 1,
    "price": "$3.99",
    "publisher": "Antarctic",
    "count": 1504
  },
  {
    "id": "betty-veronica-double-digest-archie",
    "rank": 403,
    "title": "Betty & Veronica Double Digest",
    "issue": 208,
    "price": "$3.99",
    "publisher": "Archie",
    "count": 1484
  },
  {
    "id": "archie-double-digest-archie",
    "rank": 407,
    "title": "Archie Double Digest",
    "issue": 236,
    "price": "$3.99",
    "publisher": "Archie",
    "count": 1417
  },
  {
    "id": "very-zombie-christmas-antarctic",
    "rank": 408,
    "title": "Very Zombie Christmas",
    "issue": 4,
    "price": "$3.50",
    "publisher": "Antarctic",
    "count": 1404
  }
]