[
  {
    "year": 2011,
    "month": 9,
    "count": 39313
  },
  {
    "year": 2011,
    "month": 10,
    "count": 47182
  },
  {
    "year": 2011,
    "month": 11,
    "count": 29498
  },
  {
    "year": 2011,
    "month": 12,
    "count": 26414
  },
  {
    "year": 2012,
    "month": 1,
    "count": 24485
  },
  {
    "year": 2012,
    "month": 2,
    "count": 23553
  },
  {
    "year": 2012,
    "month": 3,
    "count": 22814
  },
  {
    "year": 2012,
    "month": 4,
    "count": 22536
  },
  {
    "year": 2012,
    "month": 5,
    "count": 31413
  },
  {
    "year": 2012,
    "month": 6,
    "count": 25334
  },
  {
    "year": 2012,
    "month": 7,
    "count": 23572
  },
  {
    "year": 2012,
    "month": 8,
    "count": 22767
  },
  {
    "year": 2012,
    "month": 9,
    "count": 25388
  },
  {
    "year": 2012,
    "month": 10,
    "count": 21481
  },
  {
    "year": 2012,
    "month": 11,
    "count": 20186
  },
  {
    "year": 2012,
    "month": 12,
    "count": 19190
  },
  {
    "year": 2013,
    "month": 1,
    "count": 18254
  },
  {
    "year": 2013,
    "month": 2,
    "count": 17398
  },
  {
    "year": 2013,
    "month": 3,
    "count": 16897
  },
  {
    "year": 2013,
    "month": 4,
    "count": 16838
  },
  {
    "year": 2013,
    "month": 5,
    "count": 16184
  },
  {
    "year": 2013,
    "month": 6,
    "count": 15788
  },
  {
    "year": 2013,
    "month": 7,
    "count": 15376
  },
  {
    "year": 2013,
    "month": 8,
    "count": 15276
  },
  {
    "year": 2013,
    "month": 10,
    "count": 14378
  },
  {
    "year": 2013,
    "month": 11,
    "count": 13937
  },
  {
    "year": 2013,
    "month": 12,
    "count": 13440
  },
  {
    "year": 2014,
    "month": 1,
    "count": 13238
  },
  {
    "year": 2014,
    "month": 2,
    "count": 12782
  },
  {
    "year": 2014,
    "month": 3,
    "count": 12503
  },
  {
    "year": 2014,
    "month": 4,
    "count": 12285
  },
  {
    "year": 2014,
    "month": 5,
    "count": 12023
  },
  {
    "year": 2014,
    "month": 6,
    "count": 11675
  },
  {
    "year": 2014,
    "month": 7,
    "count": 11488
  },
  {
    "year": 2014,
    "month": 8,
    "count": 11758
  }
]