{"records":[{"issue":1,"count":20569},{"issue":2,"count":17288},{"issue":3,"count":17261},{"issue":4,"count":15689},{"issue":5,"count":15393},{"issue":6,"count":15078},{"issue":7,"count":14908},{"issue":8,"count":14443},{"issue":9,"count":14314},{"issue":10,"count":13822},{"issue":11,"count":13436},{"issue":12,"count":13254},{"issue":13,"count":13000},{"issue":14,"count":12944},{"issue":15,"count":12845},{"issue":16,"count":12682},{"issue":17,"count":12395},{"issue":18,"count":12331},{"issue":19,"count":12105},{"issue":20,"count":11828},{"issue":21,"count":11800},{"issue":22,"count":11384},{"issue":23,"count":11245},{"issue":24,"count":10924},{"issue":25,"count":10736}],"id":"conan-the-barbarian-dark-horse","title":"Conan The Barbarian","publisher":"Dark Horse"}